hi.py
py_hi-0.1.2.dist-info/entry_points.txt
py_hi-0.1.2.dist-info/LICENSE
py_hi-0.1.2.dist-info/WHEEL
py_hi-0.1.2.dist-info/METADATA
py_hi-0.1.2.dist-info/RECORD
