Metadata-Version: 2.1
Name: py-hi
Version: 0.1.2
Summary: hi is a tiny cli program that send benchmark request to almost everything based on asyncio
License: GPLV3
Keywords: benchmark,asyncio,cli
Author: Ehco1996
Author-email: zh19960202@gmail.com
Requires-Python: >=3.7,<4.0
Classifier: License :: Other/Proprietary License
Classifier: Programming Language :: Python :: 3
Classifier: Programming Language :: Python :: 3.7
Classifier: Programming Language :: Python :: 3.8
Classifier: Programming Language :: Python :: 3.9
Requires-Dist: aiohttp (>=3.7.3,<4.0.0)
Requires-Dist: rich (>=9.8.2,<10.0.0)
Requires-Dist: typer (>=0.3.2,<0.4.0)
